nanoscope/LICENSE.txt
nanoscope/__init__.py
nanoscope/constants.py
nanoscope/dll.py
nanoscope/examples.py
nanoscope/tools.py
nanoscope/Example Nanoscope Files/FV.spm
nanoscope/Example Nanoscope Files/FVHold.spm
nanoscope/Example Nanoscope Files/Force.spm
nanoscope/Example Nanoscope Files/ForceHold.spm
nanoscope/Example Nanoscope Files/ForceHoldSweep.spm
nanoscope/Example Nanoscope Files/HSDC.hsdc
nanoscope/Example Nanoscope Files/Image.spm
nanoscope/Example Nanoscope Files/NanoDrive.flt
nanoscope/Example Nanoscope Files/PeakForce.pfc
nanoscope/Example Nanoscope Files/SECMApproach.spm
nanoscope/Example Nanoscope Files/Script.spm
nanoscope/Example Nanoscope Files/ScriptModulation.spm
nanoscope/Example Nanoscope Files/ScriptTipBiasFixed.spm
nanoscope/Example Nanoscope Files/ScriptTipBiasSweep.spm
nanoscope/Example Python Files/examples.ipynb
nanoscope/Example Python Files/examples.py
nanoscope/Example Python Files/pfmexamples.ipynb
nanoscope/Example Python Files/pfmexamples.py
nanoscope/Lib/32bit/D3DX9_41.dll
nanoscope/Lib/32bit/DataCore.dll
nanoscope/Lib/32bit/DataSourceDLL.dll
nanoscope/Lib/32bit/DataSourceDLL.h
nanoscope/Lib/32bit/MathCore.dll
nanoscope/Lib/32bit/NSRS232.dll
nanoscope/Lib/32bit/NanoscopeDataFile.dll
nanoscope/Lib/32bit/SpmLabDataFile.dll
nanoscope/Lib/32bit/SystemNsCore.dll
nanoscope/Lib/32bit/VcaCore.dll
nanoscope/Lib/32bit/VersionInfo.dll
nanoscope/Lib/32bit/vControlUI.dll
nanoscope/Lib/64bit/D3DX9_41.dll
nanoscope/Lib/64bit/DataCore.dll
nanoscope/Lib/64bit/DataSourceDLL.dll
nanoscope/Lib/64bit/DataSourceDLL.h
nanoscope/Lib/64bit/MathCore.dll
nanoscope/Lib/64bit/NSRS232.dll
nanoscope/Lib/64bit/NanoscopeDataFile.dll
nanoscope/Lib/64bit/SpmLabDataFile.dll
nanoscope/Lib/64bit/SystemNsCore.dll
nanoscope/Lib/64bit/VcaCore.dll
nanoscope/Lib/64bit/VersionInfo.dll
nanoscope/Lib/64bit/vControlUI.dll
nanoscope/channels/__init__.py
nanoscope/channels/base.py
nanoscope/channels/curve.py
nanoscope/channels/curve_maker.py
nanoscope-1.2.300.dist-info/METADATA
nanoscope-1.2.300.dist-info/WHEEL
nanoscope-1.2.300.dist-info/top_level.txt
nanoscope-1.2.300.dist-info/RECORD
