Metadata-Version: 2.1
Name: nanoscope
Version: 1.2.300
Summary: Python library for Bruker AFMi Nanoscope files
Home-page: UNKNOWN
Author: Bruker Santa Barbara
Author-email: AFM.support@bruker.com
License: OSI Approved :: Apache Software License
Platform: win32
Platform: win_amd64
Classifier: Development Status :: 5 - Production/Stable
Classifier: Intended Audience :: Science/Research
Classifier: License :: OSI Approved :: Apache Software License
Classifier: Natural Language :: English
Classifier: Programming Language :: Python :: 3
Classifier: Programming Language :: Python :: 3.7
Classifier: Programming Language :: Python :: 3.8
Classifier: Programming Language :: Python :: 3.9
Classifier: Programming Language :: Python :: 3.10
Classifier: Programming Language :: Python :: 3.11
Classifier: Operating System :: Microsoft :: Windows :: Windows 10
Classifier: Topic :: Scientific/Engineering
Requires-Python: >=2.7,<=3.11.4
Requires-Dist: numpy
Requires-Dist: matplotlib
